MANIFEST.in
README.md
setup.py
django_dpa_chile.egg-info/PKG-INFO
django_dpa_chile.egg-info/SOURCES.txt
django_dpa_chile.egg-info/dependency_links.txt
django_dpa_chile.egg-info/pbr.json
django_dpa_chile.egg-info/requires.txt
django_dpa_chile.egg-info/top_level.txt
dpa_chile/__init__.py
dpa_chile/models.py
dpa_chile/management/__init__.py
dpa_chile/management/commands/__init__.py
dpa_chile/management/commands/populate_dpa_chile.py
dpa_chile/migrations/0001_initial.py
dpa_chile/migrations/__init__.py