Metadata-Version: 1.1
Name: django-dpa-chile
Version: 3.0.0
Summary: Political-Administrative Division of Chile
Home-page: https://github.com/jupitercl/django-dpa-chile
Author: Francisco Jordan
Author-email: franciscojordan@live.com
License: MIT
Keywords: django chile comunas regiones provincias
Platform: UNKNOWN
Classifier: Development Status :: 5 - Production/Stable
Classifier: Environment :: Web Environment
Classifier: Framework :: Django :: 1.11
Classifier: Intended Audience :: Developers
Classifier: License :: OSI Approved :: MIT License
Classifier: Natural Language :: Spanish
Classifier: Operating System :: Unix
Classifier: Programming Language :: Python
Classifier: Programming Language :: Python :: 2
Classifier: Programming Language :: Python :: 2.7
